{"expires":1784338491.97,"value":{"highlighted":"<!-- Syntax highlighted by torchlight.dev --><div class='line'><span style=\"color: #ABB2BF;\">rails </span><span style=\"color: #98C379;\">new</span><span style=\"color: #ABB2BF;\"> </span><span style=\"color: #98C379;\">access_lint_demo</span></div><div class='line'><span style=\"color: #56B6C2;\">cd</span><span style=\"color: #ABB2BF;\"> </span><span style=\"color: #98C379;\">access_lint_demo</span></div>","classes":"torchlight","styles":"background-color: #282c34; --theme-selection-background: #2c313a;"}}
